hart/__init__.py
hart/__main__.py
hart/config.py
hart/constants.py
hart/exceptions.py
hart/master.py
hart/minions.py
hart/roles.py
hart/ssh.py
hart/utils.py
hart/version.py
hart/cloud-init/base.sh
hart/cloud-init/master.sh
hart/cloud-init/minion.sh
hart/providers/__init__.py
hart/providers/base.py
hart/providers/digitalocean.py
hart/providers/ec2.py
hart/providers/gce.py
hart/providers/libcloud.py
hart/providers/vultr.py
hart-0.18.3.dist-info/licenses/LICENSE
hart-0.18.3.dist-info/METADATA
hart-0.18.3.dist-info/WHEEL
hart-0.18.3.dist-info/entry_points.txt
hart-0.18.3.dist-info/top_level.txt
hart-0.18.3.dist-info/RECORD
