Metadata-Version: 2.4
Name: hart
Version: 0.18.3
Summary: Opinionated salt-cloud alternative
Home-page: https://github.com/thusoy/hart
Author: Tarjei Husøy
Author-email: git@thusoy.com
Classifier: Development Status :: 4 - Beta
Classifier: Environment :: Web Environment
Classifier: Intended Audience :: System Administrators
Classifier: License :: OSI Approved :: MIT License
Classifier: Programming Language :: Python :: 3.4
Classifier: Programming Language :: Python :: 3.5
Classifier: Programming Language :: Python :: 3.6
Classifier: Programming Language :: Python :: 3.7
License-File: LICENSE
Requires-Dist: apache-libcloud>=2.6.1
Requires-Dist: jinja2
Requires-Dist: paramiko
Requires-Dist: pyyaml
Requires-Dist: toml
Requires-Dist: ifaddr
Requires-Dist: boto3
Dynamic: author
Dynamic: author-email
Dynamic: classifier
Dynamic: home-page
Dynamic: license-file
Dynamic: requires-dist
Dynamic: summary
